mcp_composer/__init__.py
mcp_composer/__main__.py
mcp_composer/cli.py
mcp_composer/a2a_service/a2a_mcp.py
mcp_composer/core/__init__.py
mcp_composer/core/composer.py
mcp_composer/core/auth_handler/.env.oauth.example
mcp_composer/core/auth_handler/__init__.py
mcp_composer/core/auth_handler/aspera_auth_handler.py
mcp_composer/core/auth_handler/dynamic_token_client.py
mcp_composer/core/auth_handler/dynamic_token_manager.py
mcp_composer/core/auth_handler/oauth.py
mcp_composer/core/auth_handler/oauth_handler.py
mcp_composer/core/auth_handler/providers.py
mcp_composer/core/auth_handler/solis_dal_jwt_handler.py
mcp_composer/core/cli/README.md
mcp_composer/core/cli/cli_main.py
mcp_composer/core/cli/cli_typer.py
mcp_composer/core/cli/middleware_cli.py
mcp_composer/core/cli/commands/__init__.py
mcp_composer/core/cli/commands/catalog_commands.py
mcp_composer/core/cli/commands/composer_commands.py
mcp_composer/core/cli/commands/config_commands.py
mcp_composer/core/cli/commands/init_commands.py
mcp_composer/core/cli/commands/middleware_commands.py
mcp_composer/core/cli/commands/tag_commands.py
mcp_composer/core/cli/generators/__init__.py
mcp_composer/core/cli/generators/project_generator.py
mcp_composer/core/config/__init__.py
mcp_composer/core/config/cli_commands.py
mcp_composer/core/config/config_loader.py
mcp_composer/core/config/unified_config.py
mcp_composer/core/member_servers/__init__.py
mcp_composer/core/member_servers/builder.py
mcp_composer/core/member_servers/layered_constants.py
mcp_composer/core/member_servers/layered_factory_oa.py
mcp_composer/core/member_servers/member_server.py
mcp_composer/core/member_servers/server_manager.py
mcp_composer/core/middleware/__init__.py
mcp_composer/core/middleware/hook_filter.py
mcp_composer/core/middleware/hook_policy.py
mcp_composer/core/middleware/middleware.py
mcp_composer/core/middleware/middleware_config.py
mcp_composer/core/middleware/middleware_manager.py
mcp_composer/core/models/__init__.py
mcp_composer-0.1.0.9.dist-info/METADATA
mcp_composer-0.1.0.9.dist-info/WHEEL
mcp_composer-0.1.0.9.dist-info/entry_points.txt
mcp_composer-0.1.0.9.dist-info/RECORD
