Metadata-Version: 2.4
Name: mcp-composer
Version: 0.1.0.9
Summary: FastMCP-based MCP Server Orchestrator
Project-URL: Documentation, https://ibm.github.io/mcp-composer/
Project-URL: Repository, https://github.com/ibm/mcp-composer
Keywords: agent,ibm,llm,mcp,mcp client,mcp developer kit,mcp server,model context protocol
Requires-Python: >=3.11
Requires-Dist: a2a-sdk==0.3.15
Requires-Dist: aiohttp==3.12.14
Requires-Dist: asyncpg>=0.29.0
Requires-Dist: deepdiff>=8.6.1
Requires-Dist: dotenv>=0.9.9
Requires-Dist: duckduckgo-search>=6.3.0
Requires-Dist: fastmcp==2.13.1
Requires-Dist: google-genai==1.51.0
Requires-Dist: httpx==0.28.1
Requires-Dist: hvac==2.3.0
Requires-Dist: ibm-cloud-sdk-core==3.23.0
Requires-Dist: ibm-secrets-manager-sdk==2.1.10
Requires-Dist: ibmcloudant==0.10.2
Requires-Dist: jsonref>=1.1.0
Requires-Dist: jsonschema>=4.24.0
Requires-Dist: litellm>=1.0.0
Requires-Dist: numpy==2.3.3
Requires-Dist: ollama>=0.6.1
Requires-Dist: pandas==2.3.3
Requires-Dist: pydantic-settings==2.10.1
Requires-Dist: pydantic==2.11.7
Requires-Dist: python-daemon>=3.1.2
Requires-Dist: pyyaml>=6.0.2
Requires-Dist: requests==2.32.4
Requires-Dist: rich>=13.7
Requires-Dist: scikit-learn>=1.7.1
Requires-Dist: typer>=0.17.0
Requires-Dist: types-requests>=2.32.4.20250611
Requires-Dist: uncurl==0.0.11
Provides-Extra: tracing
Requires-Dist: opentelemetry-api==1.38.0; extra == 'tracing'
Requires-Dist: opentelemetry-exporter-otlp==1.38.0; extra == 'tracing'
Requires-Dist: opentelemetry-sdk==1.38.0; extra == 'tracing'
